flipt_migrate/cli.py
flipt_migrate/exporter.py
flipt_migrate/models/flipt.py
flipt_migrate/source/launchdarkly.py
flipt_migrate/transformer.py
flipt_migrate-0.1.2.dist-info/LICENSE
flipt_migrate-0.1.2.dist-info/METADATA
flipt_migrate-0.1.2.dist-info/WHEEL
flipt_migrate-0.1.2.dist-info/entry_points.txt
flipt_migrate-0.1.2.dist-info/RECORD
