Metadata-Version: 2.1
Name: flipt-migrate
Version: 0.1.2
Summary: A CLI tool to migrate feature flags from one source (e.g. competitor) to Flipt
License: Apache-2.0
Author: Flipt Devs
Author-email: dev@flipt.io
Requires-Python: >=3.11,<4.0
Classifier: License :: OSI Approved :: Apache Software License
Classifier: Programming Language :: Python :: 3
Classifier: Programming Language :: Python :: 3.11
Requires-Dist: pydantic (>=2.3.0,<3.0.0)
Requires-Dist: pydantic-yaml (>=1.1.1,<2.0.0)
Requires-Dist: pyyaml (>=6.0.1,<7.0.0)
Requires-Dist: questionary (>=2.0.0,<3.0.0)
Requires-Dist: requests (>=2.31.0,<3.0.0)
